{
  "bugzilla.suse.com": {
    "user": "rbranco@suse.com",
    "api_key": "BUGZILLA_API_KEY"
  },
  "jira.suse.com": {
    "cookies": {
      "JIRASESSIONID": "JIRA_SESSION_ID",
      "atlassian.xsrf.token": "JIRA_TOKEN"
    }
  },
  "progress.opensuse.org": {
    "username": "rbranco",
    "key": "REDMINE_API_KEY"
  },
  "gitlab.suse.de": {
    "private_token": "GITLAB_API_KEY"
  },
  "gitlab.com": {
    "private_token": "GITLAB_API_KEY"
  },
  "github.com": {
    "login_or_token": "GITHUB_TOKEN"
  }
}
